AUTHORS
COPYING
MANIFEST.in
README.rst
pgzrun.py
setup.cfg
setup.py
pgzero/__init__.py
pgzero/__main__.py
pgzero/actor.py
pgzero/animation.py
pgzero/builtins.py
pgzero/clock.py
pgzero/constants.py
pgzero/game.py
pgzero/game_constant.py
pgzero/keyboard.py
pgzero/loaders.py
pgzero/music.py
pgzero/ptext.py
pgzero/rect.py
pgzero/runner.py
pgzero/screen.py
pgzero/soundfmt.py
pgzero/spellcheck.py
pgzero/storage.py
pgzero/tone.py
pgzero/data/icon.png
pgzero/data/joypad.png
pgzero_yt.egg-info/PKG-INFO
pgzero_yt.egg-info/SOURCES.txt
pgzero_yt.egg-info/dependency_links.txt
pgzero_yt.egg-info/entry_points.txt
pgzero_yt.egg-info/requires.txt
pgzero_yt.egg-info/top_level.txt